.DS_Store
.gitignore
MANIFEST.in
README.txt
setup.cfg
setup.py
collective/.DS_Store
collective/__init__.py
collective.portlet.tal.egg-info/PKG-INFO
collective.portlet.tal.egg-info/SOURCES.txt
collective.portlet.tal.egg-info/dependency_links.txt
collective.portlet.tal.egg-info/entry_points.txt
collective.portlet.tal.egg-info/namespace_packages.txt
collective.portlet.tal.egg-info/not-zip-safe
collective.portlet.tal.egg-info/requires.txt
collective.portlet.tal.egg-info/top_level.txt
collective/__pycache__/__init__.cpython-38.pyc
collective/portlet/.DS_Store
collective/portlet/__init__.py
collective/portlet/__pycache__/__init__.cpython-38.pyc
collective/portlet/tal/.DS_Store
collective/portlet/tal/__init__.py
collective/portlet/tal/configure.zcml
collective/portlet/tal/talportlet.py
collective/portlet/tal/version.txt
collective/portlet/tal/__pycache__/__init__.cpython-38.pyc
collective/portlet/tal/__pycache__/talportlet.cpython-38.pyc
collective/portlet/tal/profiles/.DS_Store
collective/portlet/tal/profiles/default/portlets.xml
collective/portlet/tal/profiles/uninstall/portlets.xml
collective/portlet/tal/tests/__init__.py
collective/portlet/tal/tests/base.py
collective/portlet/tal/tests/test_portlet.py
docs/HISTORY.txt
docs/INSTALL.txt
docs/LICENSE.GPL
docs/LICENSE.txt