Metadata-Version: 1.2
Name: collective.portlet.tal
Version: 1.2.1
Summary: TAL portlet for Plone 3, 4 and 5
Home-page: http://plone.org
Author: Martin Aspeli
Author-email: optilude@gmx.net
Maintainer: Alex Clark
Maintainer-email: aclark@aclark.net
License: GPL
Keywords: plone portlet tal
Platform: UNKNOWN
Classifier: Framework :: Plone
Classifier: Framework :: Zope2
Classifier: Framework :: Zope3
Classifier: Programming Language :: Python
Classifier: Topic :: Software Development :: Libraries :: Python Modules
